nats_callout/__init__.py
nats_callout/encoder.py
nats_callout/exceptions.py
nats_callout/jwt_tools.py
nats_callout/service.py
nats_callout/claims/__init__.py
nats_callout/claims/authorization_request.py
nats_callout/claims/authorization_response.py
nats_callout/claims/base.py
nats_callout/claims/user.py
nats_callout-0.1.1.dist-info/licenses/LICENSE
nats_callout-0.1.1.dist-info/METADATA
nats_callout-0.1.1.dist-info/WHEEL
nats_callout-0.1.1.dist-info/top_level.txt
nats_callout-0.1.1.dist-info/RECORD
