Metadata-Version: 2.4
Name: nats-callout
Version: 0.1.1
Summary: A Python library for implementing NATS Auth Callout consumers, enabling dynamic authentication and authorization for NATS clients.
Author-email: Daler Sattarov <zdaler014@gmail.com>
License-Expression: MIT
Project-URL: Homepage, https://github.com/daler-sz/nats_callout
Project-URL: Repository, https://github.com/daler-sz/nats_callout
Project-URL: Issues, https://github.com/daler-sz/nats_callout/issues
Keywords: nats,authentication,authorization,callout,jwt,nkeys
Classifier: Development Status :: 4 - Beta
Classifier: Intended Audience :: Developers
Classifier: Programming Language :: Python :: 3
Classifier: Programming Language :: Python :: 3.10
Classifier: Programming Language :: Python :: 3.11
Classifier: Programming Language :: Python :: 3.12
Classifier: Programming Language :: Python :: 3.13
Classifier: Topic :: Software Development :: Libraries :: Python Modules
Classifier: Topic :: System :: Networking
Requires-Python: >=3.10
License-File: LICENSE
Requires-Dist: nkeys>=0.2.1
Requires-Dist: pyjwt>=2.10.1
Requires-Dist: adaptix==3.0.0b11
Dynamic: license-file
